MANIFEST.in
setup.py
objs/__init__.py
objs.egg-info/PKG-INFO
objs.egg-info/SOURCES.txt
objs.egg-info/dependency_links.txt
objs.egg-info/top_level.txt
objs.egg-info/zip-safe