Metadata-Version: 1.0
Name: objs
Version: 0.0.1
Summary: object like js
Home-page: https://gitee.com/i8gua/objs
Author: zuroc
Author-email: zsp042@gmail.com
License: UNKNOWN
Platform: UNKNOWN
